  1           0 LOAD_CONST               0 (<code object fib at 0x7f35644f2ad0, file "fib.py", line 1>)
              2 LOAD_CONST               1 ('fib')
              4 MAKE_FUNCTION            0
              6 STORE_NAME               0 (fib)
              8 LOAD_CONST               2 (None)
             10 RETURN_VALUE

Disassembly of <code object fib at 0x7f35644f2ad0, file "fib.py", line 1>:
  2           0 LOAD_FAST                0 (x)
              2 LOAD_CONST               1 (2)
              4 COMPARE_OP               0 (<)
              6 POP_JUMP_IF_FALSE        6 (to 12)

  3           8 LOAD_CONST               2 (1)
             10 RETURN_VALUE

  4     >>   12 LOAD_GLOBAL              0 (fib)
             14 LOAD_FAST                0 (x)
             16 LOAD_CONST               2 (1)
             18 BINARY_SUBTRACT
             20 CALL_FUNCTION            1
             22 LOAD_GLOBAL              0 (fib)
             24 LOAD_FAST                0 (x)
             26 LOAD_CONST               1 (2)
             28 BINARY_SUBTRACT
             30 CALL_FUNCTION            1
             32 BINARY_ADD
             34 RETURN_VALUE
